swarmauri_toolkit_github/GithubBranchTool.py
swarmauri_toolkit_github/GithubCommitTool.py
swarmauri_toolkit_github/GithubIssueTool.py
swarmauri_toolkit_github/GithubPRTool.py
swarmauri_toolkit_github/GithubRepoTool.py
swarmauri_toolkit_github/GithubToolkit.py
swarmauri_toolkit_github/__init__.py
swarmauri_toolkit_github-0.7.5.dist-info/LICENSE
swarmauri_toolkit_github-0.7.5.dist-info/METADATA
swarmauri_toolkit_github-0.7.5.dist-info/WHEEL
swarmauri_toolkit_github-0.7.5.dist-info/entry_points.txt
swarmauri_toolkit_github-0.7.5.dist-info/RECORD
